snip/__init__.py
snip/_version.py
segmentation_nets_in_pytorch-0.0.1rc5.dist-info/LICENSE
segmentation_nets_in_pytorch-0.0.1rc5.dist-info/METADATA
segmentation_nets_in_pytorch-0.0.1rc5.dist-info/WHEEL
segmentation_nets_in_pytorch-0.0.1rc5.dist-info/top_level.txt
segmentation_nets_in_pytorch-0.0.1rc5.dist-info/RECORD
